{"202543031201":{"order":[{"horse_no":9,"finish":1,"odds":1.0},{"horse_no":2,"finish":2,"odds":9.0},{"horse_no":1,"finish":3,"odds":3.0},{"horse_no":10,"finish":4,"odds":10.0},{"horse_no":5,"finish":5,"odds":4.0},{"horse_no":3,"finish":6,"odds":2.0},{"horse_no":7,"finish":7,"odds":5.0},{"horse_no":4,"finish":8,"odds":6.0},{"horse_no":8,"finish":9,"odds":1.0},{"horse_no":6,"finish":10,"odds":7.0}],"payouts":{"単勝":{"combo":"9","payout":140},"複勝":{"combo":"921","payout":100490130},"馬連":{"combo":"29","payout":6430},"三連複":{"combo":"1-2-9","payout":5200},"三連単":{"combo":"9-2-1","payout":22780},"枠連":{"combo":"2-8","payout":5010},"馬単":{"combo":"9-2","payout":6990},"ワイド":[{"combo":"2-9","payout":1240},{"combo":"1-9","payout":180},{"combo":"1-2","payout":1850}]},"source":"race_results_db","wide_fix_applied":true},"202543031202":{"order":[{"horse_no":10,"finish":1,"odds":1.0},{"horse_no":7,"finish":2,"odds":2.0},{"horse_no":8,"finish":3,"odds":5.0},{"horse_no":4,"finish":4,"odds":1.0},{"horse_no":6,"finish":5,"odds":2.0},{"horse_no":1,"finish":6,"odds":5.0},{"horse_no":9,"finish":7,"odds":3.0},{"horse_no":3,"finish":8,"odds":8.0},{"horse_no":2,"finish":9,"odds":3.0},{"horse_no":5,"finish":10,"odds":5.0}],"payouts":{"単勝":{"combo":"10","payout":260},"複勝":{"combo":"1078","payout":120170570},"馬連":{"combo":"710","payout":520},"三連複":{"combo":"7-8-10","payout":3430},"三連単":{"combo":"10-7-8","payout":12320},"枠連":{"combo":"7-8","payout":420},"馬単":{"combo":"10-7","payout":1110},"ワイド":[{"combo":"7-10","payout":260},{"combo":"8-10","payout":880},{"combo":"7-8","payout":1590}]},"source":"race_results_db","wide_fix_applied":true},"202543031203":{"order":[{"horse_no":12,"finish":1,"odds":1.0},{"horse_no":3,"finish":2,"odds":6.0},{"horse_no":2,"finish":3,"odds":2.0},{"horse_no":6,"finish":4,"odds":9.0},{"horse_no":5,"finish":5,"odds":7.0},{"horse_no":1,"finish":6,"odds":11.0},{"horse_no":10,"finish":7,"odds":6.0},{"horse_no":7,"finish":8,"odds":4.0},{"horse_no":4,"finish":9,"odds":2.0},{"horse_no":9,"finish":10,"odds":12.0},{"horse_no":11,"finish":11,"odds":10.0},{"horse_no":8,"finish":12,"odds":5.0}],"payouts":{"単勝":{"combo":"12","payout":170},"複勝":{"combo":"1232","payout":100110110},"馬連":{"combo":"312","payout":260},"三連複":{"combo":"2-3-12","payout":210},"三連単":{"combo":"12-3-2","payout":910},"枠連":{"combo":"3-8","payout":250},"馬単":{"combo":"12-3","payout":370},"ワイド":[{"combo":"3-12","payout":120},{"combo":"2-12","payout":130},{"combo":"2-3","payout":170}]},"source":"race_results_db","wide_fix_applied":true},"202543031204":{"order":[{"horse_no":4,"finish":1,"odds":1.0},{"horse_no":11,"finish":2,"odds":1.0},{"horse_no":2,"finish":3,"odds":4.0},{"horse_no":9,"finish":4,"odds":2.0},{"horse_no":10,"finish":5,"odds":6.0},{"horse_no":3,"finish":6,"odds":7.0},{"horse_no":5,"finish":6,"odds":11.0},{"horse_no":7,"finish":8,"odds":1.0},{"horse_no":6,"finish":9,"odds":2.0},{"horse_no":1,"finish":10,"odds":8.0},{"horse_no":8,"finish":11,"odds":10.0},{"horse_no":12,"finish":12,"odds":5.0}],"payouts":{"単勝":{"combo":"4","payout":130},"複勝":{"combo":"4112","payout":110150780},"馬連":{"combo":"411","payout":460},"三連複":{"combo":"2-4-11","payout":8800},"三連単":{"combo":"4-11-2","payout":17190},"枠連":{"combo":"4-8","payout":430},"馬単":{"combo":"4-11","payout":610},"ワイド":[{"combo":"4-11","payout":260},{"combo":"2-4","payout":1920},{"combo":"2-11","payout":6210}]},"source":"race_results_db","wide_fix_applied":true},"202543031205":{"order":[{"horse_no":9,"finish":1,"odds":7.0},{"horse_no":4,"finish":2,"odds":3.0},{"horse_no":6,"finish":3,"odds":6.0},{"horse_no":8,"finish":4,"odds":5.0},{"horse_no":1,"finish":5,"odds":2.0},{"horse_no":5,"finish":6,"odds":8.0},{"horse_no":3,"finish":7,"odds":4.0},{"horse_no":2,"finish":8,"odds":1.0},{"horse_no":7,"finish":9,"odds":9.0}],"payouts":{"単勝":{"combo":"9","payout":1710},"複勝":{"combo":"946","payout":280180330},"馬連":{"combo":"49","payout":3950},"三連複":{"combo":"4-6-9","payout":17910},"三連単":{"combo":"9-4-6","payout":151700},"枠連":{"combo":"4-8","payout":1860},"馬単":{"combo":"9-4","payout":12140},"ワイド":[{"combo":"4-9","payout":1230},{"combo":"6-9","payout":2420},{"combo":"4-6","payout":1160}]},"source":"race_results_db","wide_fix_applied":true},"202543031206":{"order":[{"horse_no":9,"finish":1,"odds":2.0},{"horse_no":4,"finish":2,"odds":3.0},{"horse_no":3,"finish":3,"odds":5.0},{"horse_no":5,"finish":4,"odds":3.0},{"horse_no":2,"finish":5,"odds":4.0},{"horse_no":7,"finish":6,"odds":1.0},{"horse_no":1,"finish":7,"odds":1.0},{"horse_no":6,"finish":8,"odds":4.0},{"horse_no":8,"finish":9,"odds":1.0}],"payouts":{"単勝":{"combo":"9","payout":370},"複勝":{"combo":"943","payout":160140230},"馬連":{"combo":"49","payout":1000},"三連複":{"combo":"3-4-9","payout":3310},"三連単":{"combo":"9-4-3","payout":25690},"枠連":{"combo":"4-8","payout":820},"馬単":{"combo":"9-4","payout":2120},"ワイド":[{"combo":"4-9","payout":370},{"combo":"3-9","payout":960},{"combo":"3-4","payout":490}]},"source":"race_results_db","wide_fix_applied":true},"202543031207":{"order":[{"horse_no":1,"finish":1,"odds":1.0},{"horse_no":8,"finish":2,"odds":3.0},{"horse_no":10,"finish":3,"odds":2.0},{"horse_no":5,"finish":4,"odds":7.0},{"horse_no":7,"finish":5,"odds":6.0},{"horse_no":9,"finish":6,"odds":4.0},{"horse_no":2,"finish":7,"odds":1.0},{"horse_no":11,"finish":8,"odds":3.0},{"horse_no":6,"finish":9,"odds":1.0},{"horse_no":4,"finish":10,"odds":2.0}],"payouts":{"単勝":{"combo":"1","payout":210},"複勝":{"combo":"1810","payout":110140140},"馬連":{"combo":"18","payout":470},"三連複":{"combo":"1-8-10","payout":530},"三連単":{"combo":"1-8-10","payout":1650},"枠連":{"combo":"1-7","payout":260},"馬単":{"combo":"1-8","payout":710},"ワイド":[{"combo":"1-8","payout":190},{"combo":"1-10","payout":180},{"combo":"8-10","payout":240}]},"source":"race_results_db","wide_fix_applied":true},"202543031208":{"order":[{"horse_no":1,"finish":1,"odds":5.0},{"horse_no":9,"finish":2,"odds":6.0},{"horse_no":3,"finish":3,"odds":1.0},{"horse_no":7,"finish":4,"odds":4.0},{"horse_no":5,"finish":5,"odds":4.0},{"horse_no":11,"finish":6,"odds":9.0},{"horse_no":4,"finish":7,"odds":7.0},{"horse_no":2,"finish":8,"odds":8.0},{"horse_no":6,"finish":9,"odds":3.0},{"horse_no":10,"finish":10,"odds":3.0}],"payouts":{"単勝":{"combo":"1","payout":800},"複勝":{"combo":"193","payout":260230140},"馬連":{"combo":"19","payout":4200},"三連複":{"combo":"1-3-9","payout":2340},"三連単":{"combo":"1-9-3","payout":23680},"枠連":{"combo":"1-7","payout":3230},"馬単":{"combo":"1-9","payout":8770},"ワイド":[{"combo":"1-9","payout":1000},{"combo":"1-3","payout":420},{"combo":"3-9","payout":420}]},"source":"race_results_db","wide_fix_applied":true},"202543031209":{"order":[{"horse_no":6,"finish":1,"odds":1.0},{"horse_no":1,"finish":2,"odds":5.0},{"horse_no":10,"finish":3,"odds":2.0},{"horse_no":4,"finish":4,"odds":2.0},{"horse_no":8,"finish":5,"odds":9.0},{"horse_no":5,"finish":6,"odds":3.0},{"horse_no":3,"finish":7,"odds":7.0},{"horse_no":2,"finish":8,"odds":10.0},{"horse_no":7,"finish":9,"odds":4.0},{"horse_no":11,"finish":10,"odds":8.0},{"horse_no":9,"finish":11,"odds":11.0}],"payouts":{"単勝":{"combo":"6","payout":140},"複勝":{"combo":"6110","payout":100140140},"馬連":{"combo":"16","payout":470},"三連複":{"combo":"1-6-10","payout":750},"三連単":{"combo":"6-1-10","payout":1870},"枠連":{"combo":"1-6","payout":440},"馬単":{"combo":"6-1","payout":580},"ワイド":[{"combo":"1-6","payout":190},{"combo":"6-10","payout":170},{"combo":"1-10","payout":420}]},"source":"race_results_db","wide_fix_applied":true},"202543031210":{"order":[{"horse_no":1,"finish":1,"odds":2.0},{"horse_no":8,"finish":2,"odds":3.0},{"horse_no":3,"finish":3,"odds":2.0},{"horse_no":9,"finish":4,"odds":9.0},{"horse_no":4,"finish":5,"odds":3.0},{"horse_no":7,"finish":6,"odds":8.0},{"horse_no":6,"finish":7,"odds":3.0},{"horse_no":10,"finish":8,"odds":7.0},{"horse_no":5,"finish":9,"odds":3.0},{"horse_no":2,"finish":10,"odds":4.0}],"payouts":{"単勝":{"combo":"1","payout":310},"複勝":{"combo":"183","payout":120100210},"馬連":{"combo":"18","payout":230},"三連複":{"combo":"1-3-8","payout":620},"三連単":{"combo":"1-8-3","payout":2410},"枠連":{"combo":"1-7","payout":230},"馬単":{"combo":"1-8","payout":550},"ワイド":[{"combo":"1-8","payout":140},{"combo":"1-3","payout":450},{"combo":"3-8","payout":340}]},"source":"race_results_db","wide_fix_applied":true},"202543031211":{"order":[{"horse_no":13,"finish":1,"odds":2.0},{"horse_no":11,"finish":2,"odds":3.0},{"horse_no":6,"finish":3,"odds":3.0},{"horse_no":5,"finish":4,"odds":2.0},{"horse_no":3,"finish":5,"odds":4.0},{"horse_no":4,"finish":6,"odds":1.0},{"horse_no":10,"finish":7,"odds":6.0},{"horse_no":2,"finish":8,"odds":3.0},{"horse_no":7,"finish":9,"odds":3.0},{"horse_no":9,"finish":10,"odds":4.0},{"horse_no":12,"finish":11,"odds":9.0},{"horse_no":8,"finish":12,"odds":11.0},{"horse_no":1,"finish":13,"odds":13.0}],"payouts":{"単勝":{"combo":"13","payout":320},"複勝":{"combo":"13116","payout":150180230},"馬連":{"combo":"1113","payout":1000},"三連複":{"combo":"6-11-13","payout":2340},"三連単":{"combo":"13-11-6","payout":7050},"枠連":{"combo":"7-8","payout":930},"馬単":{"combo":"13-11","payout":1620},"ワイド":[{"combo":"11-13","payout":370},{"combo":"6-13","payout":520},{"combo":"6-11","payout":540}]},"source":"race_results_db","wide_fix_applied":true},"202543031212":{"order":[{"horse_no":9,"finish":1,"odds":1.0},{"horse_no":6,"finish":2,"odds":7.0},{"horse_no":3,"finish":3,"odds":6.0},{"horse_no":5,"finish":4,"odds":1.0},{"horse_no":7,"finish":5,"odds":3.0},{"horse_no":1,"finish":6,"odds":11.0},{"horse_no":10,"finish":7,"odds":4.0},{"horse_no":2,"finish":8,"odds":8.0},{"horse_no":12,"finish":9,"odds":6.0},{"horse_no":8,"finish":10,"odds":7.0},{"horse_no":4,"finish":11,"odds":13.0},{"horse_no":11,"finish":12,"odds":5.0},{"horse_no":13,"finish":13,"odds":9.0}],"payouts":{"単勝":{"combo":"9","payout":160},"複勝":{"combo":"963","payout":130300280},"馬連":{"combo":"69","payout":990},"三連複":{"combo":"3-6-9","payout":3400},"三連単":{"combo":"9-6-3","payout":10460},"枠連":{"combo":"5-6","payout":840},"馬単":{"combo":"9-6","payout":1290},"ワイド":[{"combo":"6-9","payout":430},{"combo":"3-9","payout":560},{"combo":"3-6","payout":1810}]},"source":"race_results_db","wide_fix_applied":true},"202544031201":{"order":[{"horse_no":9,"finish":1,"odds":1.0},{"horse_no":7,"finish":2,"odds":3.0},{"horse_no":1,"finish":3,"odds":4.0},{"horse_no":10,"finish":4,"odds":8.0},{"horse_no":6,"finish":5,"odds":9.0},{"horse_no":3,"finish":6,"odds":5.0},{"horse_no":2,"finish":7,"odds":2.0},{"horse_no":12,"finish":8,"odds":6.0},{"horse_no":5,"finish":9,"odds":3.0},{"horse_no":11,"finish":10,"odds":2.0},{"horse_no":8,"finish":11,"odds":7.0},{"horse_no":4,"finish":12,"odds":1.0}],"payouts":{"単勝":{"combo":"9","payout":290},"複勝":{"combo":"971","payout":120200190},"馬連":{"combo":"79","payout":1060},"三連複":{"combo":"1-7-9","payout":2160},"三連単":{"combo":"9-7-1","payout":7960},"枠連":{"combo":"6-7","payout":720},"馬単":{"combo":"9-7","payout":2060},"ワイド":[{"combo":"7-9","payout":380},{"combo":"1-9","payout":350},{"combo":"1-7","payout":700}]},"source":"race_results_db","wide_fix_applied":true},"202544031202":{"order":[{"horse_no":10,"finish":1,"odds":3.0},{"horse_no":2,"finish":2,"odds":6.0},{"horse_no":4,"finish":3,"odds":1.0},{"horse_no":14,"finish":4,"odds":2.0},{"horse_no":7,"finish":5,"odds":12.0},{"horse_no":6,"finish":6,"odds":11.0},{"horse_no":3,"finish":7,"odds":4.0},{"horse_no":1,"finish":8,"odds":8.0},{"horse_no":5,"finish":9,"odds":13.0},{"horse_no":9,"finish":10,"odds":5.0},{"horse_no":11,"finish":11,"odds":7.0},{"horse_no":8,"finish":12,"odds":9.0},{"horse_no":13,"finish":13,"odds":7.0}],"payouts":{"単勝":{"combo":"10","payout":520},"複勝":{"combo":"1024","payout":180320120},"馬連":{"combo":"210","payout":3590},"三連複":{"combo":"2-4-10","payout":2760},"三連単":{"combo":"10-2-4","payout":27950},"枠連":{"combo":"2-6","payout":1880},"馬単":{"combo":"10-2","payout":6650},"ワイド":[{"combo":"2-10","payout":930},{"combo":"4-10","payout":310},{"combo":"2-4","payout":630}]},"source":"race_results_db","wide_fix_applied":true},"202544031203":{"order":[{"horse_no":2,"finish":1,"odds":2.0},{"horse_no":12,"finish":2,"odds":6.0},{"horse_no":11,"finish":3,"odds":1.0},{"horse_no":9,"finish":4,"odds":4.0},{"horse_no":8,"finish":5,"odds":2.0},{"horse_no":13,"finish":6,"odds":7.0},{"horse_no":10,"finish":7,"odds":11.0},{"horse_no":1,"finish":8,"odds":2.0},{"horse_no":3,"finish":9,"odds":10.0},{"horse_no":7,"finish":10,"odds":8.0},{"horse_no":4,"finish":11,"odds":4.0},{"horse_no":14,"finish":12,"odds":12.0},{"horse_no":5,"finish":13,"odds":7.0},{"horse_no":6,"finish":14,"odds":7.0}],"payouts":{"単勝":{"combo":"2","payout":310},"複勝":{"combo":"21211","payout":150270120},"馬連":{"combo":"212","payout":2160},"三連複":{"combo":"2-11-12","payout":1890},"三連単":{"combo":"2-12-11","payout":11980},"枠連":{"combo":"2-7","payout":410},"馬単":{"combo":"2-12","payout":3380},"ワイド":[{"combo":"2-12","payout":800},{"combo":"2-11","payout":220},{"combo":"11-12","payout":550}]},"source":"race_results_db","wide_fix_applied":true},"202544031204":{"order":[{"horse_no":6,"finish":1,"odds":7.0},{"horse_no":9,"finish":2,"odds":2.0},{"horse_no":5,"finish":3,"odds":3.0},{"horse_no":13,"finish":4,"odds":8.0},{"horse_no":8,"finish":5,"odds":6.0},{"horse_no":10,"finish":6,"odds":11.0},{"horse_no":4,"finish":7,"odds":4.0},{"horse_no":2,"finish":8,"odds":10.0},{"horse_no":7,"finish":9,"odds":3.0},{"horse_no":12,"finish":10,"odds":9.0},{"horse_no":11,"finish":11,"odds":5.0},{"horse_no":3,"finish":12,"odds":12.0},{"horse_no":1,"finish":13,"odds":4.0}],"payouts":{"単勝":{"combo":"6","payout":2800},"複勝":{"combo":"695","payout":420120110},"馬連":{"combo":"69","payout":3400},"三連複":{"combo":"5-6-9","payout":1300},"三連単":{"combo":"6-9-5","payout":20580},"枠連":{"combo":"5-6","payout":1390},"馬単":{"combo":"6-9","payout":10190},"ワイド":[{"combo":"6-9","payout":830},{"combo":"5-6","payout":540},{"combo":"5-9","payout":160}]},"source":"race_results_db","wide_fix_applied":true},"202544031205":{"order":[{"horse_no":14,"finish":1,"odds":1.0},{"horse_no":8,"finish":2,"odds":3.0},{"horse_no":7,"finish":3,"odds":4.0},{"horse_no":13,"finish":4,"odds":6.0},{"horse_no":11,"finish":5,"odds":1.0},{"horse_no":3,"finish":6,"odds":3.0},{"horse_no":5,"finish":7,"odds":3.0},{"horse_no":4,"finish":8,"odds":5.0},{"horse_no":9,"finish":9,"odds":1.0},{"horse_no":1,"finish":10,"odds":12.0},{"horse_no":6,"finish":11,"odds":9.0},{"horse_no":2,"finish":12,"odds":4.0},{"horse_no":12,"finish":13,"odds":10.0},{"horse_no":10,"finish":14,"odds":4.0}],"payouts":{"単勝":{"combo":"14","payout":140},"複勝":{"combo":"1487","payout":110120200},"馬連":{"combo":"814","payout":220},"三連複":{"combo":"7-8-14","payout":590},"三連単":{"combo":"14-8-7","payout":1260},"枠連":{"combo":"5-8","payout":160},"馬単":{"combo":"14-8","payout":360},"ワイド":[{"combo":"8-14","payout":140},{"combo":"7-14","payout":300},{"combo":"7-8","payout":340}]},"source":"race_results_db","wide_fix_applied":true},"202544031206":{"order":[{"horse_no":8,"finish":1,"odds":3.0},{"horse_no":11,"finish":2,"odds":2.0},{"horse_no":7,"finish":3,"odds":1.0},{"horse_no":4,"finish":4,"odds":5.0},{"horse_no":6,"finish":5,"odds":8.0},{"horse_no":13,"finish":6,"odds":4.0},{"horse_no":9,"finish":7,"odds":9.0},{"horse_no":12,"finish":8,"odds":7.0},{"horse_no":10,"finish":9,"odds":10.0},{"horse_no":2,"finish":10,"odds":12.0},{"horse_no":3,"finish":11,"odds":3.0},{"horse_no":1,"finish":12,"odds":2.0},{"horse_no":5,"finish":13,"odds":13.0}],"payouts":{"単勝":{"combo":"8","payout":1660},"複勝":{"combo":"8117","payout":130100100},"馬連":{"combo":"811","payout":1280},"三連複":{"combo":"7-8-11","payout":410},"三連単":{"combo":"8-11-7","payout":9560},"枠連":{"combo":"6-7","payout":1610},"馬単":{"combo":"8-11","payout":4920},"ワイド":[{"combo":"8-11","payout":290},{"combo":"7-8","payout":210},{"combo":"7-11","payout":130}]},"source":"race_results_db","wide_fix_applied":true},"202544031207":{"order":[{"horse_no":7,"finish":1,"odds":5.0},{"horse_no":11,"finish":2,"odds":2.0},{"horse_no":5,"finish":3,"odds":8.0},{"horse_no":4,"finish":4,"odds":6.0},{"horse_no":6,"finish":5,"odds":7.0},{"horse_no":3,"finish":6,"odds":11.0},{"horse_no":1,"finish":7,"odds":2.0},{"horse_no":8,"finish":8,"odds":3.0},{"horse_no":9,"finish":9,"odds":5.0},{"horse_no":2,"finish":10,"odds":4.0},{"horse_no":10,"finish":11,"odds":4.0}],"payouts":{"単勝":{"combo":"7","payout":960},"複勝":{"combo":"7115","payout":300140390},"馬連":{"combo":"711","payout":1680},"三連複":{"combo":"5-7-11","payout":6620},"三連単":{"combo":"7-11-5","payout":43110},"枠連":{"combo":"6-8","payout":710},"馬単":{"combo":"7-11","payout":4080},"ワイド":[{"combo":"7-11","payout":680},{"combo":"5-7","payout":1890},{"combo":"5-11","payout":1240}]},"source":"race_results_db","wide_fix_applied":true},"202544031208":{"order":[{"horse_no":8,"finish":1,"odds":1.0},{"horse_no":6,"finish":2,"odds":2.0},{"horse_no":7,"finish":3,"odds":4.0},{"horse_no":9,"finish":4,"odds":2.0},{"horse_no":3,"finish":5,"odds":6.0},{"horse_no":4,"finish":6,"odds":2.0},{"horse_no":5,"finish":7,"odds":3.0},{"horse_no":1,"finish":8,"odds":9.0},{"horse_no":2,"finish":9,"odds":7.0}],"payouts":{"単勝":{"combo":"8","payout":170},"複勝":{"combo":"867","payout":100190190},"馬連":{"combo":"68","payout":520},"三連複":{"combo":"6-7-8","payout":1220},"三連単":{"combo":"8-6-7","payout":4350},"枠連":{"combo":"6-8","payout":680},"馬単":{"combo":"8-6","payout":860},"ワイド":[{"combo":"6-8","payout":240},{"combo":"7-8","payout":290},{"combo":"6-7","payout":720}]},"source":"race_results_db","wide_fix_applied":true},"202544031209":{"order":[{"horse_no":3,"finish":1,"odds":6.0},{"horse_no":8,"finish":2,"odds":8.0},{"horse_no":13,"finish":3,"odds":3.0},{"horse_no":5,"finish":4,"odds":4.0},{"horse_no":2,"finish":5,"odds":2.0},{"horse_no":6,"finish":6,"odds":10.0},{"horse_no":11,"finish":7,"odds":5.0},{"horse_no":1,"finish":8,"odds":2.0},{"horse_no":7,"finish":9,"odds":7.0},{"horse_no":12,"finish":10,"odds":12.0},{"horse_no":4,"finish":11,"odds":9.0},{"horse_no":9,"finish":12,"odds":11.0},{"horse_no":10,"finish":13,"odds":13.0}],"payouts":{"単勝":{"combo":"3","payout":1470},"複勝":{"combo":"3813","payout":420400160},"馬連":{"combo":"38","payout":9250},"三連複":{"combo":"3-8-13","payout":10540},"三連単":{"combo":"3-8-13","payout":83220},"枠連":{"combo":"3-6","payout":8050},"馬単":{"combo":"3-8","payout":14990},"ワイド":[{"combo":"3-8","payout":2480},{"combo":"3-13","payout":770},{"combo":"8-13","payout":1240}]},"source":"race_results_db","wide_fix_applied":true},"202544031210":{"order":[{"horse_no":12,"finish":1,"odds":3.0},{"horse_no":8,"finish":2,"odds":1.0},{"horse_no":4,"finish":3,"odds":8.0},{"horse_no":11,"finish":4,"odds":4.0},{"horse_no":5,"finish":5,"odds":2.0},{"horse_no":7,"finish":6,"odds":1.0},{"horse_no":9,"finish":7,"odds":9.0},{"horse_no":1,"finish":8,"odds":10.0},{"horse_no":10,"finish":9,"odds":11.0},{"horse_no":6,"finish":10,"odds":2.0},{"horse_no":3,"finish":11,"odds":7.0},{"horse_no":2,"finish":12,"odds":12.0}],"payouts":{"単勝":{"combo":"12","payout":480},"複勝":{"combo":"1284","payout":160280420},"馬連":{"combo":"812","payout":2660},"三連複":{"combo":"4-8-12","payout":12310},"三連単":{"combo":"12-8-4","payout":57430},"枠連":{"combo":"6-8","payout":360},"馬単":{"combo":"12-8","payout":4080},"ワイド":[{"combo":"8-12","payout":950},{"combo":"4-12","payout":1310},{"combo":"4-8","payout":2550}]},"source":"race_results_db","wide_fix_applied":true},"202544031211":{"order":[{"horse_no":6,"finish":1,"odds":1.0},{"horse_no":8,"finish":2,"odds":1.0},{"horse_no":5,"finish":3,"odds":2.0},{"horse_no":7,"finish":4,"odds":3.0},{"horse_no":3,"finish":5,"odds":1.0},{"horse_no":2,"finish":6,"odds":7.0},{"horse_no":4,"finish":7,"odds":9.0},{"horse_no":9,"finish":8,"odds":6.0},{"horse_no":1,"finish":9,"odds":2.0}],"payouts":{"単勝":{"combo":"6","payout":160},"複勝":{"combo":"685","payout":100100140},"馬連":{"combo":"68","payout":160},"三連複":{"combo":"5-6-8","payout":240},"三連単":{"combo":"6-8-5","payout":570},"枠連":{"combo":"6-8","payout":170},"馬単":{"combo":"6-8","payout":310},"ワイド":[{"combo":"6-8","payout":110},{"combo":"5-6","payout":160},{"combo":"5-8","payout":180}]},"source":"race_results_db","wide_fix_applied":true},"202544031212":{"order":[{"horse_no":3,"finish":1,"odds":1.0},{"horse_no":7,"finish":2,"odds":7.0},{"horse_no":13,"finish":3,"odds":6.0},{"horse_no":11,"finish":4,"odds":9.0},{"horse_no":1,"finish":5,"odds":10.0},{"horse_no":4,"finish":6,"odds":8.0},{"horse_no":14,"finish":7,"odds":1.0},{"horse_no":8,"finish":8,"odds":5.0},{"horse_no":6,"finish":9,"odds":11.0},{"horse_no":10,"finish":10,"odds":3.0},{"horse_no":15,"finish":11,"odds":2.0},{"horse_no":2,"finish":12,"odds":15.0},{"horse_no":12,"finish":13,"odds":12.0},{"horse_no":9,"finish":14,"odds":5.0},{"horse_no":5,"finish":15,"odds":13.0}],"payouts":{"単勝":{"combo":"3","payout":190},"複勝":{"combo":"3713","payout":140480360},"馬連":{"combo":"37","payout":2000},"三連複":{"combo":"3-7-13","payout":7330},"三連単":{"combo":"3-7-13","payout":24790},"枠連":{"combo":"2-4","payout":1480},"馬単":{"combo":"3-7","payout":2620},"ワイド":[{"combo":"3-7","payout":830},{"combo":"3-13","payout":660},{"combo":"7-13","payout":3120}]},"source":"race_results_db","wide_fix_applied":true},"202548031201":{"order":[{"horse_no":12,"finish":1,"odds":2.0},{"horse_no":10,"finish":2,"odds":4.0},{"horse_no":5,"finish":3,"odds":1.0},{"horse_no":6,"finish":4,"odds":5.0},{"horse_no":8,"finish":5,"odds":3.0},{"horse_no":11,"finish":6,"odds":9.0},{"horse_no":4,"finish":7,"odds":3.0},{"horse_no":3,"finish":8,"odds":7.0},{"horse_no":7,"finish":9,"odds":2.0},{"horse_no":9,"finish":10,"odds":8.0},{"horse_no":1,"finish":11,"odds":2.0},{"horse_no":2,"finish":12,"odds":3.0}],"payouts":{"単勝":{"combo":"12","payout":310},"複勝":{"combo":"12105","payout":180300140},"馬連":{"combo":"1012","payout":1280},"三連複":{"combo":"5-10-12","payout":570},"三連単":{"combo":"12-10-5","payout":4560},"枠連":{"combo":"7-8","payout":1750},"馬単":{"combo":"12-10","payout":2020},"ワイド":[{"combo":"10-12","payout":350},{"combo":"5-12","payout":180},{"combo":"5-10","payout":320}]},"source":"race_results_db","wide_fix_applied":true},"202548031202":{"order":[{"horse_no":11,"finish":1,"odds":2.0},{"horse_no":8,"finish":2,"odds":3.0},{"horse_no":9,"finish":3,"odds":5.0},{"horse_no":10,"finish":4,"odds":9.0},{"horse_no":4,"finish":5,"odds":7.0},{"horse_no":1,"finish":6,"odds":3.0},{"horse_no":3,"finish":7,"odds":8.0},{"horse_no":12,"finish":8,"odds":6.0},{"horse_no":6,"finish":9,"odds":11.0},{"horse_no":7,"finish":10,"odds":12.0},{"horse_no":2,"finish":11,"odds":10.0},{"horse_no":5,"finish":12,"odds":4.0}],"payouts":{"単勝":{"combo":"11","payout":390},"複勝":{"combo":"1189","payout":130150170},"馬連":{"combo":"811","payout":280},"三連複":{"combo":"8-9-11","payout":840},"三連単":{"combo":"11-8-9","payout":3540},"枠連":{"combo":"6-8","payout":310},"馬単":{"combo":"11-8","payout":960},"ワイド":[{"combo":"8-11","payout":170},{"combo":"9-11","payout":430},{"combo":"8-9","payout":360}]},"source":"race_results_db","wide_fix_applied":true},"202548031203":{"order":[{"horse_no":6,"finish":1,"odds":1.0},{"horse_no":8,"finish":2,"odds":1.0},{"horse_no":11,"finish":3,"odds":7.0},{"horse_no":12,"finish":4,"odds":3.0},{"horse_no":4,"finish":5,"odds":10.0},{"horse_no":5,"finish":6,"odds":6.0},{"horse_no":2,"finish":7,"odds":5.0},{"horse_no":10,"finish":8,"odds":11.0},{"horse_no":7,"finish":9,"odds":2.0},{"horse_no":1,"finish":10,"odds":12.0},{"horse_no":9,"finish":11,"odds":3.0},{"horse_no":3,"finish":12,"odds":7.0}],"payouts":{"単勝":{"combo":"6","payout":130},"複勝":{"combo":"6811","payout":110110380},"馬連":{"combo":"68","payout":200},"三連複":{"combo":"6-8-11","payout":2530},"三連単":{"combo":"6-8-11","payout":6550},"枠連":{"combo":"5-6","payout":140},"馬単":{"combo":"6-8","payout":350},"ワイド":[{"combo":"6-8","payout":140},{"combo":"6-11","payout":830},{"combo":"8-11","payout":1220}]},"source":"race_results_db","wide_fix_applied":true},"202548031204":{"order":[{"horse_no":4,"finish":1,"odds":12.0},{"horse_no":8,"finish":2,"odds":5.0},{"horse_no":10,"finish":3,"odds":3.0},{"horse_no":3,"finish":4,"odds":7.0},{"horse_no":6,"finish":5,"odds":6.0},{"horse_no":9,"finish":6,"odds":1.0},{"horse_no":1,"finish":7,"odds":4.0},{"horse_no":12,"finish":8,"odds":1.0},{"horse_no":2,"finish":9,"odds":3.0},{"horse_no":5,"finish":10,"odds":9.0},{"horse_no":11,"finish":11,"odds":11.0},{"horse_no":7,"finish":12,"odds":3.0}],"payouts":{"単勝":{"combo":"4","payout":15370},"複勝":{"combo":"4810","payout":1590190150},"馬連":{"combo":"48","payout":37750},"三連複":{"combo":"4-8-10","payout":25920},"三連単":{"combo":"4-8-10","payout":531780},"枠連":{"combo":"4-6","payout":28520},"馬単":{"combo":"4-8","payout":117510},"ワイド":[{"combo":"4-8","payout":5570},{"combo":"4-10","payout":4740},{"combo":"8-10","payout":450}]},"source":"race_results_db","wide_fix_applied":true},"202548031205":{"order":[{"horse_no":1,"finish":1,"odds":1.0},{"horse_no":12,"finish":2,"odds":8.0},{"horse_no":7,"finish":3,"odds":9.0},{"horse_no":11,"finish":4,"odds":2.0},{"horse_no":5,"finish":5,"odds":6.0},{"horse_no":4,"finish":6,"odds":4.0},{"horse_no":10,"finish":7,"odds":11.0},{"horse_no":9,"finish":8,"odds":8.0},{"horse_no":8,"finish":9,"odds":12.0},{"horse_no":3,"finish":10,"odds":7.0},{"horse_no":6,"finish":11,"odds":2.0},{"horse_no":2,"finish":12,"odds":10.0}],"payouts":{"単勝":{"combo":"1","payout":150},"複勝":{"combo":"1127","payout":150180980},"馬連":{"combo":"112","payout":230},"三連複":{"combo":"1-7-12","payout":5050},"三連単":{"combo":"1-12-7","payout":8600},"枠連":{"combo":"1-8","payout":210},"馬単":{"combo":"1-12","payout":340},"ワイド":[{"combo":"1-12","payout":160},{"combo":"1-7","payout":2130},{"combo":"7-12","payout":3370}]},"source":"race_results_db","wide_fix_applied":true},"202548031206":{"order":[{"horse_no":1,"finish":1,"odds":1.0},{"horse_no":12,"finish":2,"odds":2.0},{"horse_no":9,"finish":3,"odds":5.0},{"horse_no":6,"finish":4,"odds":8.0},{"horse_no":11,"finish":5,"odds":3.0},{"horse_no":8,"finish":6,"odds":9.0},{"horse_no":4,"finish":7,"odds":7.0},{"horse_no":5,"finish":8,"odds":6.0},{"horse_no":7,"finish":9,"odds":4.0},{"horse_no":3,"finish":10,"odds":11.0},{"horse_no":10,"finish":11,"odds":5.0},{"horse_no":2,"finish":12,"odds":12.0}],"payouts":{"単勝":{"combo":"1","payout":160},"複勝":{"combo":"1129","payout":110140190},"馬連":{"combo":"112","payout":380},"三連複":{"combo":"1-9-12","payout":1140},"三連単":{"combo":"1-12-9","payout":2700},"枠連":{"combo":"1-8","payout":220},"馬単":{"combo":"1-12","payout":430},"ワイド":[{"combo":"1-12","payout":180},{"combo":"1-9","payout":280},{"combo":"9-12","payout":370}]},"source":"race_results_db","wide_fix_applied":true},"202548031207":{"order":[{"horse_no":9,"finish":1,"odds":6.0},{"horse_no":12,"finish":2,"odds":2.0},{"horse_no":11,"finish":3,"odds":2.0},{"horse_no":1,"finish":4,"odds":9.0},{"horse_no":8,"finish":5,"odds":10.0},{"horse_no":6,"finish":6,"odds":7.0},{"horse_no":10,"finish":7,"odds":3.0},{"horse_no":7,"finish":8,"odds":8.0},{"horse_no":5,"finish":9,"odds":1.0},{"horse_no":2,"finish":10,"odds":12.0},{"horse_no":4,"finish":11,"odds":1.0},{"horse_no":3,"finish":12,"odds":5.0}],"payouts":{"単勝":{"combo":"9","payout":1380},"複勝":{"combo":"91211","payout":380140120},"馬連":{"combo":"912","payout":3280},"三連複":{"combo":"9-11-12","payout":5560},"三連単":{"combo":"9-12-11","payout":48600},"枠連":{"combo":"7-8","payout":710},"馬単":{"combo":"9-12","payout":8950},"ワイド":[{"combo":"9-12","payout":1230},{"combo":"9-11","payout":1150},{"combo":"11-12","payout":390}]},"source":"race_results_db","wide_fix_applied":true},"202548031208":{"order":[{"horse_no":6,"finish":1,"odds":1.0},{"horse_no":10,"finish":2,"odds":3.0},{"horse_no":5,"finish":3,"odds":4.0},{"horse_no":12,"finish":4,"odds":7.0},{"horse_no":3,"finish":5,"odds":4.0},{"horse_no":4,"finish":6,"odds":8.0},{"horse_no":11,"finish":7,"odds":9.0},{"horse_no":2,"finish":8,"odds":2.0},{"horse_no":9,"finish":9,"odds":1.0},{"horse_no":7,"finish":10,"odds":10.0},{"horse_no":1,"finish":11,"odds":4.0}],"payouts":{"単勝":{"combo":"6","payout":280},"複勝":{"combo":"6105","payout":110120150},"馬連":{"combo":"610","payout":460},"三連複":{"combo":"5-6-10","payout":2330},"三連単":{"combo":"6-10-5","payout":7550},"枠連":{"combo":"5-7","payout":480},"馬単":{"combo":"6-10","payout":950},"ワイド":[{"combo":"6-10","payout":220},{"combo":"5-6","payout":510},{"combo":"5-10","payout":690}]},"source":"race_results_db","wide_fix_applied":true},"202548031209":{"order":[{"horse_no":9,"finish":1,"odds":2.0},{"horse_no":8,"finish":2,"odds":1.0},{"horse_no":6,"finish":3,"odds":3.0},{"horse_no":5,"finish":4,"odds":6.0},{"horse_no":3,"finish":5,"odds":4.0},{"horse_no":12,"finish":6,"odds":7.0},{"horse_no":7,"finish":7,"odds":3.0},{"horse_no":1,"finish":8,"odds":7.0},{"horse_no":10,"finish":9,"odds":10.0},{"horse_no":2,"finish":10,"odds":1.0},{"horse_no":11,"finish":11,"odds":2.0},{"horse_no":4,"finish":12,"odds":3.0}],"payouts":{"単勝":{"combo":"9","payout":420},"複勝":{"combo":"986","payout":130110160},"馬連":{"combo":"89","payout":360},"三連複":{"combo":"6-8-9","payout":670},"三連単":{"combo":"9-8-6","payout":3420},"枠連":{"combo":"6-7","payout":340},"馬単":{"combo":"9-8","payout":890},"ワイド":[{"combo":"8-9","payout":170},{"combo":"6-9","payout":380},{"combo":"6-8","payout":250}]},"source":"race_results_db","wide_fix_applied":true},"202548031210":{"order":[{"horse_no":3,"finish":1,"odds":1.0},{"horse_no":8,"finish":2,"odds":4.0},{"horse_no":5,"finish":3,"odds":4.0},{"horse_no":10,"finish":4,"odds":1.0},{"horse_no":7,"finish":5,"odds":11.0},{"horse_no":11,"finish":6,"odds":1.0},{"horse_no":1,"finish":7,"odds":2.0},{"horse_no":2,"finish":8,"odds":4.0},{"horse_no":4,"finish":9,"odds":8.0},{"horse_no":9,"finish":10,"odds":7.0},{"horse_no":12,"finish":11,"odds":6.0},{"horse_no":6,"finish":12,"odds":5.0}],"payouts":{"単勝":{"combo":"3","payout":330},"複勝":{"combo":"385","payout":160130150},"馬連":{"combo":"38","payout":440},"三連複":{"combo":"3-5-8","payout":930},"三連単":{"combo":"3-8-5","payout":4500},"枠連":{"combo":"3-6","payout":670},"馬単":{"combo":"3-8","payout":950},"ワイド":[{"combo":"3-8","payout":250},{"combo":"3-5","payout":360},{"combo":"5-8","payout":410}]},"source":"race_results_db","wide_fix_applied":true},"202548031211":{"order":[{"horse_no":5,"finish":1,"odds":1.0},{"horse_no":10,"finish":2,"odds":3.0},{"horse_no":12,"finish":3,"odds":7.0},{"horse_no":11,"finish":4,"odds":10.0},{"horse_no":2,"finish":5,"odds":11.0},{"horse_no":9,"finish":6,"odds":2.0},{"horse_no":7,"finish":7,"odds":4.0},{"horse_no":8,"finish":8,"odds":5.0},{"horse_no":6,"finish":9,"odds":6.0},{"horse_no":1,"finish":10,"odds":12.0},{"horse_no":4,"finish":11,"odds":2.0},{"horse_no":3,"finish":12,"odds":4.0}],"payouts":{"単勝":{"combo":"5","payout":160},"複勝":{"combo":"51012","payout":120140500},"馬連":{"combo":"510","payout":390},"三連複":{"combo":"5-10-12","payout":3950},"三連単":{"combo":"5-10-12","payout":9040},"枠連":{"combo":"5-7","payout":190},"馬単":{"combo":"5-10","payout":550},"ワイド":[{"combo":"5-10","payout":220},{"combo":"5-12","payout":1050},{"combo":"10-12","payout":1630}]},"source":"race_results_db","wide_fix_applied":true},"202548031212":{"order":[{"horse_no":6,"finish":1,"odds":2.0},{"horse_no":5,"finish":2,"odds":5.0},{"horse_no":3,"finish":3,"odds":8.0},{"horse_no":9,"finish":4,"odds":5.0},{"horse_no":8,"finish":5,"odds":2.0},{"horse_no":10,"finish":6,"odds":3.0},{"horse_no":1,"finish":7,"odds":1.0},{"horse_no":2,"finish":8,"odds":1.0},{"horse_no":4,"finish":9,"odds":5.0},{"horse_no":12,"finish":10,"odds":4.0},{"horse_no":11,"finish":11,"odds":9.0},{"horse_no":7,"finish":12,"odds":8.0}],"payouts":{"単勝":{"combo":"6","payout":290},"複勝":{"combo":"653","payout":120180420},"馬連":{"combo":"56","payout":780},"三連複":{"combo":"3-5-6","payout":4500},"三連単":{"combo":"6-5-3","payout":13750},"枠連":{"combo":"5-5","payout":930},"馬単":{"combo":"6-5","payout":1410},"ワイド":[{"combo":"5-6","payout":400},{"combo":"3-6","payout":860},{"combo":"3-5","payout":2360}]},"source":"race_results_db","wide_fix_applied":true},"202550031201":{"order":[{"horse_no":7,"finish":1,"odds":1.0},{"horse_no":6,"finish":2,"odds":2.0},{"horse_no":2,"finish":3,"odds":7.0},{"horse_no":12,"finish":4,"odds":5.0},{"horse_no":3,"finish":5,"odds":10.0},{"horse_no":8,"finish":6,"odds":3.0},{"horse_no":1,"finish":7,"odds":4.0},{"horse_no":5,"finish":8,"odds":1.0},{"horse_no":10,"finish":9,"odds":8.0},{"horse_no":4,"finish":10,"odds":5.0},{"horse_no":9,"finish":11,"odds":11.0},{"horse_no":11,"finish":12,"odds":12.0}],"payouts":{"単勝":{"combo":"7","payout":170},"複勝":{"combo":"762","payout":100100590},"馬連":{"combo":"67","payout":110},"三連複":{"combo":"2-6-7","payout":1660},"三連単":{"combo":"7-6-2","payout":4030},"枠連":{"combo":"5-6","payout":100},"馬単":{"combo":"7-6","payout":230},"ワイド":[{"combo":"6-7","payout":110},{"combo":"2-7","payout":1160},{"combo":"2-6","payout":1310}]},"source":"race_results_db","wide_fix_applied":true},"202550031202":{"order":[{"horse_no":4,"finish":1,"odds":5.0},{"horse_no":2,"finish":2,"odds":2.0},{"horse_no":5,"finish":3,"odds":3.0},{"horse_no":9,"finish":4,"odds":4.0},{"horse_no":8,"finish":5,"odds":1.0},{"horse_no":3,"finish":6,"odds":9.0},{"horse_no":7,"finish":7,"odds":2.0},{"horse_no":1,"finish":8,"odds":1.0},{"horse_no":10,"finish":9,"odds":11.0},{"horse_no":12,"finish":10,"odds":8.0},{"horse_no":6,"finish":11,"odds":5.0},{"horse_no":11,"finish":12,"odds":10.0}],"payouts":{"単勝":{"combo":"4","payout":1880},"複勝":{"combo":"425","payout":4101101580},"馬連":{"combo":"24","payout":1860},"三連複":{"combo":"2-4-5","payout":31160},"三連単":{"combo":"4-2-5","payout":226770},"枠連":{"combo":"2-4","payout":1930},"馬単":{"combo":"4-2","payout":6240},"ワイド":[{"combo":"2-4","payout":970},{"combo":"4-5","payout":14460},{"combo":"2-5","payout":3100}]},"source":"race_results_db","wide_fix_applied":true},"202550031203":{"order":[{"horse_no":7,"finish":1,"odds":1.0},{"horse_no":11,"finish":2,"odds":2.0},{"horse_no":1,"finish":3,"odds":5.0},{"horse_no":12,"finish":4,"odds":9.0},{"horse_no":4,"finish":5,"odds":3.0},{"horse_no":5,"finish":6,"odds":2.0},{"horse_no":8,"finish":7,"odds":5.0},{"horse_no":9,"finish":8,"odds":8.0},{"horse_no":2,"finish":9,"odds":4.0},{"horse_no":10,"finish":10,"odds":11.0},{"horse_no":6,"finish":11,"odds":1.0},{"horse_no":3,"finish":12,"odds":10.0}],"payouts":{"単勝":{"combo":"7","payout":150},"複勝":{"combo":"7111","payout":100310240},"馬連":{"combo":"711","payout":900},"三連複":{"combo":"1-7-11","payout":3100},"三連単":{"combo":"7-11-1","payout":6090},"枠連":{"combo":"6-8","payout":380},"馬単":{"combo":"7-11","payout":900},"ワイド":[{"combo":"7-11","payout":460},{"combo":"1-7","payout":380},{"combo":"1-11","payout":2470}]},"source":"race_results_db","wide_fix_applied":true},"202550031204":{"order":[{"horse_no":2,"finish":1,"odds":6.0},{"horse_no":5,"finish":2,"odds":1.0},{"horse_no":1,"finish":3,"odds":7.0},{"horse_no":6,"finish":4,"odds":3.0},{"horse_no":3,"finish":5,"odds":2.0},{"horse_no":4,"finish":6,"odds":5.0},{"horse_no":10,"finish":7,"odds":8.0},{"horse_no":9,"finish":8,"odds":7.0},{"horse_no":8,"finish":9,"odds":4.0},{"horse_no":7,"finish":10,"odds":10.0}],"payouts":{"単勝":{"combo":"2","payout":2050},"複勝":{"combo":"251","payout":630140220},"馬連":{"combo":"25","payout":2050},"三連複":{"combo":"1-2-5","payout":5140},"三連単":{"combo":"2-5-1","payout":38600},"枠連":{"combo":"2-5","payout":2120},"馬単":{"combo":"2-5","payout":5240},"ワイド":[{"combo":"2-5","payout":970},{"combo":"1-2","payout":2140},{"combo":"1-5","payout":420}]},"source":"race_results_db","wide_fix_applied":true},"202550031205":{"order":[{"horse_no":8,"finish":1,"odds":1.0},{"horse_no":1,"finish":2,"odds":2.0},{"horse_no":10,"finish":3,"odds":2.0},{"horse_no":7,"finish":4,"odds":6.0},{"horse_no":3,"finish":5,"odds":7.0},{"horse_no":5,"finish":6,"odds":4.0},{"horse_no":6,"finish":7,"odds":3.0},{"horse_no":11,"finish":8,"odds":8.0},{"horse_no":9,"finish":9,"odds":10.0},{"horse_no":2,"finish":10,"odds":3.0},{"horse_no":4,"finish":11,"odds":6.0}],"payouts":{"単勝":{"combo":"8","payout":170},"複勝":{"combo":"8110","payout":120180230},"馬連":{"combo":"18","payout":510},"三連複":{"combo":"1-8-10","payout":1410},"三連単":{"combo":"8-1-10","payout":4590},"枠連":{"combo":"1-7","payout":560},"馬単":{"combo":"8-1","payout":1020},"ワイド":[{"combo":"1-8","payout":290},{"combo":"8-10","payout":340},{"combo":"1-10","payout":620}]},"source":"race_results_db","wide_fix_applied":true},"202550031206":{"order":[{"horse_no":6,"finish":1,"odds":1.0},{"horse_no":9,"finish":2,"odds":2.0},{"horse_no":11,"finish":3,"odds":5.0},{"horse_no":4,"finish":4,"odds":9.0},{"horse_no":7,"finish":5,"odds":3.0},{"horse_no":1,"finish":6,"odds":4.0},{"horse_no":2,"finish":7,"odds":6.0},{"horse_no":3,"finish":8,"odds":10.0},{"horse_no":8,"finish":9,"odds":2.0},{"horse_no":5,"finish":10,"odds":7.0},{"horse_no":10,"finish":11,"odds":7.0}],"payouts":{"単勝":{"combo":"6","payout":210},"複勝":{"combo":"6911","payout":120130230},"馬連":{"combo":"69","payout":490},"三連複":{"combo":"6-9-11","payout":1420},"三連単":{"combo":"6-9-11","payout":4100},"枠連":{"combo":"6-7","payout":280},"馬単":{"combo":"6-9","payout":860},"ワイド":[{"combo":"6-9","payout":220},{"combo":"6-11","payout":550},{"combo":"9-11","payout":510}]},"source":"race_results_db","wide_fix_applied":true},"202550031207":{"order":[{"horse_no":6,"finish":1,"odds":1.0},{"horse_no":7,"finish":2,"odds":5.0},{"horse_no":1,"finish":3,"odds":2.0},{"horse_no":10,"finish":4,"odds":1.0},{"horse_no":8,"finish":5,"odds":5.0},{"horse_no":5,"finish":6,"odds":6.0},{"horse_no":3,"finish":7,"odds":4.0},{"horse_no":12,"finish":8,"odds":3.0},{"horse_no":4,"finish":9,"odds":12.0},{"horse_no":2,"finish":10,"odds":8.0},{"horse_no":11,"finish":11,"odds":7.0},{"horse_no":9,"finish":12,"odds":7.0}],"payouts":{"単勝":{"combo":"6","payout":200},"複勝":{"combo":"671","payout":110560130},"馬連":{"combo":"67","payout":3260},"三連複":{"combo":"1-6-7","payout":3030},"三連単":{"combo":"6-7-1","payout":16290},"枠連":{"combo":"5-6","payout":580},"馬単":{"combo":"6-7","payout":5190},"ワイド":[{"combo":"6-7","payout":1140},{"combo":"1-6","payout":170},{"combo":"1-7","payout":1680}]},"source":"race_results_db","wide_fix_applied":true},"202550031208":{"order":[{"horse_no":9,"finish":1,"odds":6.0},{"horse_no":7,"finish":2,"odds":7.0},{"horse_no":4,"finish":3,"odds":9.0},{"horse_no":8,"finish":4,"odds":8.0},{"horse_no":6,"finish":5,"odds":4.0},{"horse_no":3,"finish":6,"odds":1.0},{"horse_no":1,"finish":7,"odds":3.0},{"horse_no":2,"finish":8,"odds":2.0},{"horse_no":5,"finish":9,"odds":5.0}],"payouts":{"単勝":{"combo":"9","payout":1250},"複勝":{"combo":"974","payout":4704301320},"馬連":{"combo":"79","payout":7740},"三連複":{"combo":"4-7-9","payout":78270},"三連単":{"combo":"9-7-4","payout":680130},"枠連":{"combo":"7-8","payout":3110},"馬単":{"combo":"9-7","payout":15100},"ワイド":[{"combo":"7-9","payout":2130},{"combo":"4-9","payout":6740},{"combo":"4-7","payout":12440}]},"source":"race_results_db","wide_fix_applied":true},"202550031209":{"order":[{"horse_no":8,"finish":1,"odds":1.0},{"horse_no":6,"finish":2,"odds":3.0},{"horse_no":3,"finish":3,"odds":3.0},{"horse_no":9,"finish":4,"odds":8.0},{"horse_no":1,"finish":5,"odds":2.0},{"horse_no":10,"finish":6,"odds":9.0},{"horse_no":2,"finish":7,"odds":7.0},{"horse_no":5,"finish":8,"odds":4.0}],"payouts":{"単勝":{"combo":"8","payout":100},"複勝":{"combo":"863","payout":100140260},"馬連":{"combo":"68","payout":630},"三連複":{"combo":"3-6-8","payout":2040},"三連単":{"combo":"8-6-3","payout":3700},"枠連":{"combo":"6-7","payout":600},"馬単":{"combo":"8-6","payout":580},"ワイド":[{"combo":"6-8","payout":240},{"combo":"3-8","payout":410},{"combo":"3-6","payout":1740}]},"source":"race_results_db","wide_fix_applied":true},"202550031210":{"order":[{"horse_no":5,"finish":1,"odds":1.0},{"horse_no":8,"finish":2,"odds":6.0},{"horse_no":3,"finish":3,"odds":4.0},{"horse_no":9,"finish":4,"odds":7.0},{"horse_no":7,"finish":5,"odds":5.0},{"horse_no":2,"finish":6,"odds":3.0},{"horse_no":1,"finish":7,"odds":8.0},{"horse_no":4,"finish":8,"odds":1.0},{"horse_no":6,"finish":9,"odds":9.0}],"payouts":{"単勝":{"combo":"5","payout":110},"複勝":{"combo":"583","payout":100330170},"馬連":{"combo":"58","payout":1740},"三連複":{"combo":"3-5-8","payout":2910},"三連単":{"combo":"5-8-3","payout":8450},"枠連":{"combo":"5-8","payout":560},"馬単":{"combo":"5-8","payout":1790},"ワイド":[{"combo":"5-8","payout":390},{"combo":"3-5","payout":230},{"combo":"3-8","payout":1780}]},"source":"race_results_db","wide_fix_applied":true},"202550031211":{"order":[{"horse_no":7,"finish":1,"odds":5.0},{"horse_no":1,"finish":2,"odds":1.0},{"horse_no":6,"finish":3,"odds":4.0},{"horse_no":4,"finish":4,"odds":4.0},{"horse_no":2,"finish":5,"odds":4.0},{"horse_no":3,"finish":6,"odds":6.0},{"horse_no":5,"finish":7,"odds":8.0},{"horse_no":8,"finish":8,"odds":3.0},{"horse_no":9,"finish":9,"odds":9.0}],"payouts":{"単勝":{"combo":"7","payout":1750},"複勝":{"combo":"716","payout":180100190},"馬連":{"combo":"17","payout":920},"三連複":{"combo":"1-6-7","payout":2030},"三連単":{"combo":"7-1-6","payout":28570},"枠連":{"combo":"1-7","payout":730},"馬単":{"combo":"7-1","payout":4190},"ワイド":[{"combo":"1-7","payout":270},{"combo":"6-7","payout":1080},{"combo":"1-6","payout":350}]},"source":"race_results_db","wide_fix_applied":true},"202550031212":{"order":[{"horse_no":3,"finish":1,"odds":1.0},{"horse_no":7,"finish":2,"odds":9.0},{"horse_no":2,"finish":3,"odds":5.0},{"horse_no":5,"finish":4,"odds":2.0},{"horse_no":11,"finish":5,"odds":6.0},{"horse_no":1,"finish":6,"odds":11.0},{"horse_no":8,"finish":7,"odds":8.0},{"horse_no":9,"finish":8,"odds":3.0},{"horse_no":6,"finish":9,"odds":1.0},{"horse_no":10,"finish":10,"odds":7.0},{"horse_no":4,"finish":11,"odds":1.0}],"payouts":{"単勝":{"combo":"3","payout":170},"複勝":{"combo":"372","payout":1201690310},"馬連":{"combo":"37","payout":7310},"三連複":{"combo":"2-3-7","payout":19190},"三連単":{"combo":"3-7-2","payout":81630},"枠連":{"combo":"3-6","payout":830},"馬単":{"combo":"3-7","payout":11620},"ワイド":[{"combo":"3-7","payout":2370},{"combo":"2-3","payout":320},{"combo":"2-7","payout":10330}]},"source":"race_results_db","wide_fix_applied":true},"202554031201":{"order":[{"horse_no":7,"finish":1,"odds":1.0},{"horse_no":10,"finish":2,"odds":4.0},{"horse_no":6,"finish":3,"odds":4.0},{"horse_no":8,"finish":4,"odds":1.0},{"horse_no":5,"finish":5,"odds":6.0},{"horse_no":1,"finish":6,"odds":5.0},{"horse_no":9,"finish":7,"odds":4.0},{"horse_no":11,"finish":8,"odds":1.0},{"horse_no":3,"finish":9,"odds":5.0},{"horse_no":4,"finish":10,"odds":3.0},{"horse_no":2,"finish":11,"odds":10.0}],"payouts":{"単勝":{"combo":"7","payout":140},"複勝":{"combo":"7106","payout":100120170},"馬連":{"combo":"710","payout":150},"三連複":{"combo":"6-7-10","payout":360},"三連単":{"combo":"7-10-6","payout":650},"枠連":{"combo":"6-8","payout":170},"馬単":{"combo":"7-10","payout":200},"ワイド":[{"combo":"7-10","payout":120},{"combo":"6-7","payout":200},{"combo":"6-10","payout":420}]},"source":"race_results_db","wide_fix_applied":true},"202554031202":{"order":[{"horse_no":3,"finish":1,"odds":1.0},{"horse_no":9,"finish":2,"odds":7.0},{"horse_no":5,"finish":3,"odds":3.0},{"horse_no":10,"finish":4,"odds":1.0},{"horse_no":2,"finish":5,"odds":5.0},{"horse_no":4,"finish":6,"odds":3.0},{"horse_no":8,"finish":7,"odds":2.0},{"horse_no":6,"finish":8,"odds":1.0},{"horse_no":7,"finish":9,"odds":5.0},{"horse_no":1,"finish":10,"odds":10.0}],"payouts":{"単勝":{"combo":"3","payout":120},"複勝":{"combo":"395","payout":100160270},"馬連":{"combo":"39","payout":430},"三連複":{"combo":"3-5-9","payout":2380},"三連単":{"combo":"3-9-5","payout":5060},"枠連":{"combo":"3-8","payout":250},"馬単":{"combo":"3-9","payout":420},"ワイド":[{"combo":"3-9","payout":180},{"combo":"3-5","payout":500},{"combo":"5-9","payout":1690}]},"source":"race_results_db","wide_fix_applied":true},"202554031203":{"order":[{"horse_no":2,"finish":1,"odds":1.0},{"horse_no":7,"finish":2,"odds":3.0},{"horse_no":8,"finish":3,"odds":2.0},{"horse_no":9,"finish":4,"odds":6.0},{"horse_no":4,"finish":5,"odds":4.0},{"horse_no":6,"finish":6,"odds":7.0},{"horse_no":1,"finish":7,"odds":1.0},{"horse_no":3,"finish":8,"odds":3.0}],"payouts":{"単勝":{"combo":"2","payout":110},"複勝":{"combo":"278","payout":100320140},"馬連":{"combo":"27","payout":2260},"三連複":{"combo":"2-7-8","payout":810},"三連単":{"combo":"2-7-8","payout":4500},"枠連":{"combo":"2-7","payout":1810},"馬単":{"combo":"2-7","payout":2590},"ワイド":[{"combo":"2-7","payout":380},{"combo":"2-8","payout":160},{"combo":"7-8","payout":600}]},"source":"race_results_db","wide_fix_applied":true},"202554031204":{"order":[{"horse_no":5,"finish":1,"odds":1.0},{"horse_no":3,"finish":2,"odds":3.0},{"horse_no":4,"finish":3,"odds":4.0},{"horse_no":7,"finish":4,"odds":1.0},{"horse_no":6,"finish":5,"odds":4.0},{"horse_no":1,"finish":6,"odds":7.0},{"horse_no":2,"finish":7,"odds":9.0},{"horse_no":8,"finish":8,"odds":8.0},{"horse_no":9,"finish":9,"odds":4.0}],"payouts":{"単勝":{"combo":"5","payout":110},"複勝":{"combo":"534","payout":100100180},"馬連":{"combo":"35","payout":170},"三連複":{"combo":"3-4-5","payout":530},"三連単":{"combo":"5-3-4","payout":800},"枠連":{"combo":"3-5","payout":150},"馬単":{"combo":"5-3","payout":220},"ワイド":[{"combo":"3-5","payout":100},{"combo":"4-5","payout":230},{"combo":"3-4","payout":520}]},"source":"race_results_db","wide_fix_applied":true},"202554031205":{"order":[{"horse_no":3,"finish":1,"odds":1.0},{"horse_no":5,"finish":2,"odds":3.0},{"horse_no":4,"finish":3,"odds":3.0},{"horse_no":1,"finish":4,"odds":1.0},{"horse_no":10,"finish":5,"odds":9.0},{"horse_no":2,"finish":6,"odds":10.0},{"horse_no":11,"finish":7,"odds":4.0},{"horse_no":8,"finish":8,"odds":6.0},{"horse_no":6,"finish":9,"odds":7.0},{"horse_no":7,"finish":10,"odds":11.0},{"horse_no":9,"finish":11,"odds":9.0}],"payouts":{"単勝":{"combo":"3","payout":130},"複勝":{"combo":"354","payout":100150110},"馬連":{"combo":"35","payout":470},"三連複":{"combo":"3-4-5","payout":500},"三連単":{"combo":"3-5-4","payout":2000},"枠連":{"combo":"3-5","payout":600},"馬単":{"combo":"3-5","payout":650},"ワイド":[{"combo":"3-5","payout":220},{"combo":"3-4","payout":140},{"combo":"4-5","payout":430}]},"source":"race_results_db","wide_fix_applied":true},"202554031206":{"order":[{"horse_no":6,"finish":1,"odds":1.0},{"horse_no":5,"finish":2,"odds":5.0},{"horse_no":12,"finish":3,"odds":4.0},{"horse_no":4,"finish":4,"odds":3.0},{"horse_no":1,"finish":5,"odds":6.0},{"horse_no":8,"finish":6,"odds":2.0},{"horse_no":2,"finish":7,"odds":7.0},{"horse_no":7,"finish":8,"odds":2.0},{"horse_no":3,"finish":9,"odds":3.0},{"horse_no":11,"finish":10,"odds":8.0},{"horse_no":9,"finish":11,"odds":10.0}],"payouts":{"単勝":{"combo":"6","payout":230},"複勝":{"combo":"6512","payout":150230180},"馬連":{"combo":"56","payout":1330},"三連複":{"combo":"5-6-12","payout":2740},"三連単":{"combo":"6-5-12","payout":16380},"枠連":{"combo":"5-5","payout":1530},"馬単":{"combo":"6-5","payout":3110},"ワイド":[{"combo":"5-6","payout":470},{"combo":"6-12","payout":370},{"combo":"5-12","payout":1050}]},"source":"race_results_db","wide_fix_applied":true},"202554031207":{"order":[{"horse_no":11,"finish":1,"odds":2.0},{"horse_no":6,"finish":2,"odds":1.0},{"horse_no":2,"finish":3,"odds":3.0},{"horse_no":4,"finish":4,"odds":5.0},{"horse_no":7,"finish":5,"odds":10.0},{"horse_no":1,"finish":6,"odds":3.0},{"horse_no":5,"finish":7,"odds":4.0},{"horse_no":9,"finish":7,"odds":12.0},{"horse_no":8,"finish":9,"odds":2.0},{"horse_no":12,"finish":10,"odds":11.0},{"horse_no":10,"finish":11,"odds":3.0},{"horse_no":3,"finish":12,"odds":5.0}],"payouts":{"単勝":{"combo":"11","payout":490},"複勝":{"combo":"1162","payout":140120160},"馬連":{"combo":"611","payout":460},"三連複":{"combo":"2-6-11","payout":710},"三連単":{"combo":"11-6-2","payout":4880},"枠連":{"combo":"5-8","payout":380},"馬単":{"combo":"11-6","payout":1270},"ワイド":[{"combo":"6-11","payout":240},{"combo":"2-11","payout":390},{"combo":"2-6","payout":260}]},"source":"race_results_db","wide_fix_applied":true},"202554031208":{"order":[{"horse_no":4,"finish":1,"odds":2.0},{"horse_no":3,"finish":2,"odds":6.0},{"horse_no":7,"finish":3,"odds":1.0},{"horse_no":6,"finish":4,"odds":2.0},{"horse_no":5,"finish":5,"odds":3.0},{"horse_no":1,"finish":6,"odds":8.0},{"horse_no":2,"finish":6,"odds":4.0},{"horse_no":8,"finish":8,"odds":7.0}],"payouts":{"単勝":{"combo":"4","payout":330},"複勝":{"combo":"437","payout":140340560},"馬連":{"combo":"34","payout":2650},"三連複":{"combo":"3-4-7","payout":9540},"三連単":{"combo":"4-3-7","payout":34650},"馬単":{"combo":"4-3","payout":4720},"ワイド":[{"combo":"3-4","payout":1000},{"combo":"4-7","payout":1410},{"combo":"3-7","payout":2410}]},"source":"race_results_db","wide_fix_applied":true},"202554031209":{"order":[{"horse_no":4,"finish":1,"odds":8.0},{"horse_no":2,"finish":2,"odds":3.0},{"horse_no":11,"finish":3,"odds":11.0},{"horse_no":7,"finish":4,"odds":1.0},{"horse_no":5,"finish":5,"odds":12.0},{"horse_no":3,"finish":6,"odds":5.0},{"horse_no":6,"finish":7,"odds":10.0},{"horse_no":9,"finish":8,"odds":9.0},{"horse_no":12,"finish":9,"odds":2.0},{"horse_no":1,"finish":10,"odds":7.0},{"horse_no":10,"finish":11,"odds":4.0},{"horse_no":8,"finish":12,"odds":4.0}],"payouts":{"単勝":{"combo":"4","payout":1110},"複勝":{"combo":"4211","payout":280260930},"馬連":{"combo":"24","payout":3080},"三連複":{"combo":"2-4-11","payout":23650},"三連単":{"combo":"4-2-11","payout":136200},"枠連":{"combo":"2-4","payout":2740},"馬単":{"combo":"4-2","payout":6300},"ワイド":[{"combo":"2-4","payout":1250},{"combo":"4-11","payout":3830},{"combo":"2-11","payout":2910}]},"source":"race_results_db","wide_fix_applied":true}}